README.md
setup.py
graphene_sa_optimizer/__init__.py
graphene_sa_optimizer/optimize.py
graphene_sa_optimizer.egg-info/PKG-INFO
graphene_sa_optimizer.egg-info/SOURCES.txt
graphene_sa_optimizer.egg-info/dependency_links.txt
graphene_sa_optimizer.egg-info/top_level.txt
test/test_it_does_joined_load.py
test/test_it_fetches_results.py