Metadata-Version: 2.1
Name: graphene-sa-optimizer
Version: 0.0.5
Summary: Use GraphQL and SQL Alchemy for efficient database access.
Home-page: https://github.com/colanconnon/graphene_sa_optimizer
Author: Colan Connon
Author-email: cconnon11@gmail.com
License: MIT
Keywords: graphene sqlalchemy flask graphql
Platform: UNKNOWN
Classifier: License :: OSI Approved :: MIT License
Classifier: Programming Language :: Python :: 3
Classifier: Programming Language :: Python :: 3.5
Classifier: Programming Language :: Python :: 3.6
Classifier: Programming Language :: Python :: 3.7
